pyristretto/__init__.py
pyristretto/msm.cp312-win_amd64.pyd
pyristretto/msm.pyi
pyristretto/pyristretto.cp312-win_amd64.pyd
pyristretto/pyristretto.pyi
pyristretto-0.1.0.dist-info/licenses/LICENSE
pyristretto-0.1.0.dist-info/METADATA
pyristretto-0.1.0.dist-info/WHEEL
pyristretto-0.1.0.dist-info/top_level.txt
pyristretto-0.1.0.dist-info/RECORD
