Metadata-Version: 2.4
Name: pyristretto
Version: 0.1.0
Summary: Accelerated Ristretto255 primitives for Python, backed by libsodium.
Author: Xylen
License: MIT
License-File: LICENSE
Dynamic: author
Dynamic: description
Dynamic: description-content-type
Dynamic: license
Dynamic: license-file
Dynamic: summary
